[{"name":"darq","qualifiedName":"darq","href":"darq/darq-library.html","type":"library","overriddenDepth":0},{"name":"AsyncIterableExtensions","qualifiedName":"darq.AsyncIterableExtensions","href":"darq/AsyncIterableExtensions.html","type":"extension","overriddenDepth":0,"enclosedBy":{"name":"darq","type":"library"}},{"name":"awaitAll","qualifiedName":"darq.AsyncIterableExtensions.awaitAll","href":"darq/AsyncIterableExtensions/awaitAll.html","type":"method","overriddenDepth":0,"enclosedBy":{"name":"AsyncIterableExtensions","type":"extension"}},{"name":"awaitAny","qualifiedName":"darq.AsyncIterableExtensions.awaitAny","href":"darq/AsyncIterableExtensions/awaitAny.html","type":"method","overriddenDepth":0,"enclosedBy":{"name":"AsyncIterableExtensions","type":"extension"}},{"name":"BooleanConsumerExtensions","qualifiedName":"darq.BooleanConsumerExtensions","href":"darq/BooleanConsumerExtensions.html","type":"extension","overriddenDepth":0,"enclosedBy":{"name":"darq","type":"library"}},{"name":"all","qualifiedName":"darq.BooleanConsumerExtensions.all","href":"darq/BooleanConsumerExtensions/all.html","type":"method","overriddenDepth":0,"enclosedBy":{"name":"BooleanConsumerExtensions","type":"extension"}},{"name":"assertAll","qualifiedName":"darq.BooleanConsumerExtensions.assertAll","href":"darq/BooleanConsumerExtensions/assertAll.html","type":"method","overriddenDepth":0,"enclosedBy":{"name":"BooleanConsumerExtensions","type":"extension"}},{"name":"assertAny","qualifiedName":"darq.BooleanConsumerExtensions.assertAny","href":"darq/BooleanConsumerExtensions/assertAny.html","type":"method","overriddenDepth":0,"enclosedBy":{"name":"BooleanConsumerExtensions","type":"extension"}},{"name":"assertCount","qualifiedName":"darq.BooleanConsumerExtensions.assertCount","href":"darq/BooleanConsumerExtensions/assertCount.html","type":"method","overriddenDepth":0,"enclosedBy":{"name":"BooleanConsumerExtensions","type":"extension"}},{"name":"atLeast","qualifiedName":"darq.BooleanConsumerExtensions.atLeast","href":"darq/BooleanConsumerExtensions/atLeast.html","type":"method","overriddenDepth":0,"enclosedBy":{"name":"BooleanConsumerExtensions","type":"extension"}},{"name":"atMost","qualifiedName":"darq.BooleanConsumerExtensions.atMost","href":"darq/BooleanConsumerExtensions/atMost.html","type":"method","overriddenDepth":0,"enclosedBy":{"name":"BooleanConsumerExtensions","type":"extension"}},{"name":"between","qualifiedName":"darq.BooleanConsumerExtensions.between","href":"darq/BooleanConsumerExtensions/between.html","type":"method","overriddenDepth":0,"enclosedBy":{"name":"BooleanConsumerExtensions","type":"extension"}},{"name":"endsWith","qualifiedName":"darq.BooleanConsumerExtensions.endsWith","href":"darq/BooleanConsumerExtensions/endsWith.html","type":"method","overriddenDepth":0,"enclosedBy":{"name":"BooleanConsumerExtensions","type":"extension"}},{"name":"sequenceEqual","qualifiedName":"darq.BooleanConsumerExtensions.sequenceEqual","href":"darq/BooleanConsumerExtensions/sequenceEqual.html","type":"method","overriddenDepth":0,"enclosedBy":{"name":"BooleanConsumerExtensions","type":"extension"}},{"name":"startsWith","qualifiedName":"darq.BooleanConsumerExtensions.startsWith","href":"darq/BooleanConsumerExtensions/startsWith.html","type":"method","overriddenDepth":0,"enclosedBy":{"name":"BooleanConsumerExtensions","type":"extension"}},{"name":"CheckedConsumerExtensions","qualifiedName":"darq.CheckedConsumerExtensions","href":"darq/CheckedConsumerExtensions.html","type":"extension","overriddenDepth":0,"enclosedBy":{"name":"darq","type":"library"}},{"name":"defaultIfEmpty","qualifiedName":"darq.CheckedConsumerExtensions.defaultIfEmpty","href":"darq/CheckedConsumerExtensions/defaultIfEmpty.html","type":"method","overriddenDepth":0,"enclosedBy":{"name":"CheckedConsumerExtensions","type":"extension"}},{"name":"defaultRangeIfEmpty","qualifiedName":"darq.CheckedConsumerExtensions.defaultRangeIfEmpty","href":"darq/CheckedConsumerExtensions/defaultRangeIfEmpty.html","type":"method","overriddenDepth":0,"enclosedBy":{"name":"CheckedConsumerExtensions","type":"extension"}},{"name":"elementAtOrDefault","qualifiedName":"darq.CheckedConsumerExtensions.elementAtOrDefault","href":"darq/CheckedConsumerExtensions/elementAtOrDefault.html","type":"method","overriddenDepth":0,"enclosedBy":{"name":"CheckedConsumerExtensions","type":"extension"}},{"name":"firstOrDefault","qualifiedName":"darq.CheckedConsumerExtensions.firstOrDefault","href":"darq/CheckedConsumerExtensions/firstOrDefault.html","type":"method","overriddenDepth":0,"enclosedBy":{"name":"CheckedConsumerExtensions","type":"extension"}},{"name":"firstWhereOrDefault","qualifiedName":"darq.CheckedConsumerExtensions.firstWhereOrDefault","href":"darq/CheckedConsumerExtensions/firstWhereOrDefault.html","type":"method","overriddenDepth":0,"enclosedBy":{"name":"CheckedConsumerExtensions","type":"extension"}},{"name":"lastOrDefault","qualifiedName":"darq.CheckedConsumerExtensions.lastOrDefault","href":"darq/CheckedConsumerExtensions/lastOrDefault.html","type":"method","overriddenDepth":0,"enclosedBy":{"name":"CheckedConsumerExtensions","type":"extension"}},{"name":"lastWhereOrDefault","qualifiedName":"darq.CheckedConsumerExtensions.lastWhereOrDefault","href":"darq/CheckedConsumerExtensions/lastWhereOrDefault.html","type":"method","overriddenDepth":0,"enclosedBy":{"name":"CheckedConsumerExtensions","type":"extension"}},{"name":"singleOrDefault","qualifiedName":"darq.CheckedConsumerExtensions.singleOrDefault","href":"darq/CheckedConsumerExtensions/singleOrDefault.html","type":"method","overriddenDepth":0,"enclosedBy":{"name":"CheckedConsumerExtensions","type":"extension"}},{"name":"singleWhereOrDefault","qualifiedName":"darq.CheckedConsumerExtensions.singleWhereOrDefault","href":"darq/CheckedConsumerExtensions/singleWhereOrDefault.html","type":"method","overriddenDepth":0,"enclosedBy":{"name":"CheckedConsumerExtensions","type":"extension"}},{"name":"Comparer","qualifiedName":"darq.Comparer","href":"darq/Comparer.html","type":"typedef","overriddenDepth":0,"enclosedBy":{"name":"darq","type":"library"}},{"name":"ComparisonConsumerExtensions","qualifiedName":"darq.ComparisonConsumerExtensions","href":"darq/ComparisonConsumerExtensions.html","type":"extension","overriddenDepth":0,"enclosedBy":{"name":"darq","type":"library"}},{"name":"compareCount","qualifiedName":"darq.ComparisonConsumerExtensions.compareCount","href":"darq/ComparisonConsumerExtensions/compareCount.html","type":"method","overriddenDepth":0,"enclosedBy":{"name":"ComparisonConsumerExtensions","type":"extension"}},{"name":"ConversionConsumerExtensions","qualifiedName":"darq.ConversionConsumerExtensions","href":"darq/ConversionConsumerExtensions.html","type":"extension","overriddenDepth":0,"enclosedBy":{"name":"darq","type":"library"}},{"name":"toHashMap","qualifiedName":"darq.ConversionConsumerExtensions.toHashMap","href":"darq/ConversionConsumerExtensions/toHashMap.html","type":"method","overriddenDepth":0,"enclosedBy":{"name":"ConversionConsumerExtensions","type":"extension"}},{"name":"toLinkedHashMap","qualifiedName":"darq.ConversionConsumerExtensions.toLinkedHashMap","href":"darq/ConversionConsumerExtensions/toLinkedHashMap.html","type":"method","overriddenDepth":0,"enclosedBy":{"name":"ConversionConsumerExtensions","type":"extension"}},{"name":"toMap","qualifiedName":"darq.ConversionConsumerExtensions.toMap","href":"darq/ConversionConsumerExtensions/toMap.html","type":"method","overriddenDepth":0,"enclosedBy":{"name":"ConversionConsumerExtensions","type":"extension"}},{"name":"toSplayTreeMap","qualifiedName":"darq.ConversionConsumerExtensions.toSplayTreeMap","href":"darq/ConversionConsumerExtensions/toSplayTreeMap.html","type":"method","overriddenDepth":0,"enclosedBy":{"name":"ConversionConsumerExtensions","type":"extension"}},{"name":"toStream","qualifiedName":"darq.ConversionConsumerExtensions.toStream","href":"darq/ConversionConsumerExtensions/toStream.html","type":"method","overriddenDepth":0,"enclosedBy":{"name":"ConversionConsumerExtensions","type":"extension"}},{"name":"EqualityComparer","qualifiedName":"darq.EqualityComparer","href":"darq/EqualityComparer-class.html","type":"class","overriddenDepth":0,"enclosedBy":{"name":"darq","type":"library"}},{"name":"operator ==","qualifiedName":"darq.EqualityComparer.==","href":"darq/EqualityComparer/operator_equals.html","type":"method","overriddenDepth":0,"enclosedBy":{"name":"EqualityComparer","type":"class"}},{"name":"EqualityComparer","qualifiedName":"darq.EqualityComparer.EqualityComparer","href":"darq/EqualityComparer/EqualityComparer.html","type":"constructor","overriddenDepth":0,"enclosedBy":{"name":"EqualityComparer","type":"class"}},{"name":"compare","qualifiedName":"darq.EqualityComparer.compare","href":"darq/EqualityComparer/compare.html","type":"property","overriddenDepth":0,"enclosedBy":{"name":"EqualityComparer","type":"class"}},{"name":"forType","qualifiedName":"darq.EqualityComparer.forType","href":"darq/EqualityComparer/forType.html","type":"method","overriddenDepth":0,"enclosedBy":{"name":"EqualityComparer","type":"class"}},{"name":"hash","qualifiedName":"darq.EqualityComparer.hash","href":"darq/EqualityComparer/hash.html","type":"property","overriddenDepth":0,"enclosedBy":{"name":"EqualityComparer","type":"class"}},{"name":"hashCode","qualifiedName":"darq.EqualityComparer.hashCode","href":"darq/EqualityComparer/hashCode.html","type":"property","overriddenDepth":0,"enclosedBy":{"name":"EqualityComparer","type":"class"}},{"name":"noSuchMethod","qualifiedName":"darq.EqualityComparer.noSuchMethod","href":"darq/EqualityComparer/noSuchMethod.html","type":"method","overriddenDepth":0,"enclosedBy":{"name":"EqualityComparer","type":"class"}},{"name":"registerEqualityComparer","qualifiedName":"darq.EqualityComparer.registerEqualityComparer","href":"darq/EqualityComparer/registerEqualityComparer.html","type":"method","overriddenDepth":0,"enclosedBy":{"name":"EqualityComparer","type":"class"}},{"name":"runtimeType","qualifiedName":"darq.EqualityComparer.runtimeType","href":"darq/EqualityComparer/runtimeType.html","type":"property","overriddenDepth":0,"enclosedBy":{"name":"EqualityComparer","type":"class"}},{"name":"sort","qualifiedName":"darq.EqualityComparer.sort","href":"darq/EqualityComparer/sort.html","type":"property","overriddenDepth":0,"enclosedBy":{"name":"EqualityComparer","type":"class"}},{"name":"toString","qualifiedName":"darq.EqualityComparer.toString","href":"darq/EqualityComparer/toString.html","type":"method","overriddenDepth":0,"enclosedBy":{"name":"EqualityComparer","type":"class"}},{"name":"unregisterEqualityComparer","qualifiedName":"darq.EqualityComparer.unregisterEqualityComparer","href":"darq/EqualityComparer/unregisterEqualityComparer.html","type":"method","overriddenDepth":0,"enclosedBy":{"name":"EqualityComparer","type":"class"}},{"name":"GroupedIterableExtensions","qualifiedName":"darq.GroupedIterableExtensions","href":"darq/GroupedIterableExtensions.html","type":"extension","overriddenDepth":0,"enclosedBy":{"name":"darq","type":"library"}},{"name":"batch","qualifiedName":"darq.GroupedIterableExtensions.batch","href":"darq/GroupedIterableExtensions/batch.html","type":"method","overriddenDepth":0,"enclosedBy":{"name":"GroupedIterableExtensions","type":"extension"}},{"name":"batchSelect","qualifiedName":"darq.GroupedIterableExtensions.batchSelect","href":"darq/GroupedIterableExtensions/batchSelect.html","type":"method","overriddenDepth":0,"enclosedBy":{"name":"GroupedIterableExtensions","type":"extension"}},{"name":"groupBy","qualifiedName":"darq.GroupedIterableExtensions.groupBy","href":"darq/GroupedIterableExtensions/groupBy.html","type":"method","overriddenDepth":0,"enclosedBy":{"name":"GroupedIterableExtensions","type":"extension"}},{"name":"groupByValue","qualifiedName":"darq.GroupedIterableExtensions.groupByValue","href":"darq/GroupedIterableExtensions/groupByValue.html","type":"method","overriddenDepth":0,"enclosedBy":{"name":"GroupedIterableExtensions","type":"extension"}},{"name":"groupJoin","qualifiedName":"darq.GroupedIterableExtensions.groupJoin","href":"darq/GroupedIterableExtensions/groupJoin.html","type":"method","overriddenDepth":0,"enclosedBy":{"name":"GroupedIterableExtensions","type":"extension"}},{"name":"groupSelect","qualifiedName":"darq.GroupedIterableExtensions.groupSelect","href":"darq/GroupedIterableExtensions/groupSelect.html","type":"method","overriddenDepth":0,"enclosedBy":{"name":"GroupedIterableExtensions","type":"extension"}},{"name":"groupSelectValue","qualifiedName":"darq.GroupedIterableExtensions.groupSelectValue","href":"darq/GroupedIterableExtensions/groupSelectValue.html","type":"method","overriddenDepth":0,"enclosedBy":{"name":"GroupedIterableExtensions","type":"extension"}},{"name":"pairwise","qualifiedName":"darq.GroupedIterableExtensions.pairwise","href":"darq/GroupedIterableExtensions/pairwise.html","type":"method","overriddenDepth":0,"enclosedBy":{"name":"GroupedIterableExtensions","type":"extension"}},{"name":"partition","qualifiedName":"darq.GroupedIterableExtensions.partition","href":"darq/GroupedIterableExtensions/partition.html","type":"method","overriddenDepth":0,"enclosedBy":{"name":"GroupedIterableExtensions","type":"extension"}},{"name":"Hasher","qualifiedName":"darq.Hasher","href":"darq/Hasher.html","type":"typedef","overriddenDepth":0,"enclosedBy":{"name":"darq","type":"library"}},{"name":"InsertionIterableExtensions","qualifiedName":"darq.InsertionIterableExtensions","href":"darq/InsertionIterableExtensions.html","type":"extension","overriddenDepth":0,"enclosedBy":{"name":"darq","type":"library"}},{"name":"append","qualifiedName":"darq.InsertionIterableExtensions.append","href":"darq/InsertionIterableExtensions/append.html","type":"method","overriddenDepth":0,"enclosedBy":{"name":"InsertionIterableExtensions","type":"extension"}},{"name":"append2","qualifiedName":"darq.InsertionIterableExtensions.append2","href":"darq/InsertionIterableExtensions/append2.html","type":"method","overriddenDepth":0,"enclosedBy":{"name":"InsertionIterableExtensions","type":"extension"}},{"name":"append3","qualifiedName":"darq.InsertionIterableExtensions.append3","href":"darq/InsertionIterableExtensions/append3.html","type":"method","overriddenDepth":0,"enclosedBy":{"name":"InsertionIterableExtensions","type":"extension"}},{"name":"append4","qualifiedName":"darq.InsertionIterableExtensions.append4","href":"darq/InsertionIterableExtensions/append4.html","type":"method","overriddenDepth":0,"enclosedBy":{"name":"InsertionIterableExtensions","type":"extension"}},{"name":"append5","qualifiedName":"darq.InsertionIterableExtensions.append5","href":"darq/InsertionIterableExtensions/append5.html","type":"method","overriddenDepth":0,"enclosedBy":{"name":"InsertionIterableExtensions","type":"extension"}},{"name":"append6","qualifiedName":"darq.InsertionIterableExtensions.append6","href":"darq/InsertionIterableExtensions/append6.html","type":"method","overriddenDepth":0,"enclosedBy":{"name":"InsertionIterableExtensions","type":"extension"}},{"name":"append7","qualifiedName":"darq.InsertionIterableExtensions.append7","href":"darq/InsertionIterableExtensions/append7.html","type":"method","overriddenDepth":0,"enclosedBy":{"name":"InsertionIterableExtensions","type":"extension"}},{"name":"append8","qualifiedName":"darq.InsertionIterableExtensions.append8","href":"darq/InsertionIterableExtensions/append8.html","type":"method","overriddenDepth":0,"enclosedBy":{"name":"InsertionIterableExtensions","type":"extension"}},{"name":"append9","qualifiedName":"darq.InsertionIterableExtensions.append9","href":"darq/InsertionIterableExtensions/append9.html","type":"method","overriddenDepth":0,"enclosedBy":{"name":"InsertionIterableExtensions","type":"extension"}},{"name":"appendAll","qualifiedName":"darq.InsertionIterableExtensions.appendAll","href":"darq/InsertionIterableExtensions/appendAll.html","type":"method","overriddenDepth":0,"enclosedBy":{"name":"InsertionIterableExtensions","type":"extension"}},{"name":"concat","qualifiedName":"darq.InsertionIterableExtensions.concat","href":"darq/InsertionIterableExtensions/concat.html","type":"method","overriddenDepth":0,"enclosedBy":{"name":"InsertionIterableExtensions","type":"extension"}},{"name":"concat2","qualifiedName":"darq.InsertionIterableExtensions.concat2","href":"darq/InsertionIterableExtensions/concat2.html","type":"method","overriddenDepth":0,"enclosedBy":{"name":"InsertionIterableExtensions","type":"extension"}},{"name":"concat3","qualifiedName":"darq.InsertionIterableExtensions.concat3","href":"darq/InsertionIterableExtensions/concat3.html","type":"method","overriddenDepth":0,"enclosedBy":{"name":"InsertionIterableExtensions","type":"extension"}},{"name":"concat4","qualifiedName":"darq.InsertionIterableExtensions.concat4","href":"darq/InsertionIterableExtensions/concat4.html","type":"method","overriddenDepth":0,"enclosedBy":{"name":"InsertionIterableExtensions","type":"extension"}},{"name":"concat5","qualifiedName":"darq.InsertionIterableExtensions.concat5","href":"darq/InsertionIterableExtensions/concat5.html","type":"method","overriddenDepth":0,"enclosedBy":{"name":"InsertionIterableExtensions","type":"extension"}},{"name":"concat6","qualifiedName":"darq.InsertionIterableExtensions.concat6","href":"darq/InsertionIterableExtensions/concat6.html","type":"method","overriddenDepth":0,"enclosedBy":{"name":"InsertionIterableExtensions","type":"extension"}},{"name":"concat7","qualifiedName":"darq.InsertionIterableExtensions.concat7","href":"darq/InsertionIterableExtensions/concat7.html","type":"method","overriddenDepth":0,"enclosedBy":{"name":"InsertionIterableExtensions","type":"extension"}},{"name":"concat8","qualifiedName":"darq.InsertionIterableExtensions.concat8","href":"darq/InsertionIterableExtensions/concat8.html","type":"method","overriddenDepth":0,"enclosedBy":{"name":"InsertionIterableExtensions","type":"extension"}},{"name":"concat9","qualifiedName":"darq.InsertionIterableExtensions.concat9","href":"darq/InsertionIterableExtensions/concat9.html","type":"method","overriddenDepth":0,"enclosedBy":{"name":"InsertionIterableExtensions","type":"extension"}},{"name":"concatAll","qualifiedName":"darq.InsertionIterableExtensions.concatAll","href":"darq/InsertionIterableExtensions/concatAll.html","type":"method","overriddenDepth":0,"enclosedBy":{"name":"InsertionIterableExtensions","type":"extension"}},{"name":"exclude","qualifiedName":"darq.InsertionIterableExtensions.exclude","href":"darq/InsertionIterableExtensions/exclude.html","type":"method","overriddenDepth":0,"enclosedBy":{"name":"InsertionIterableExtensions","type":"extension"}},{"name":"excludeAt","qualifiedName":"darq.InsertionIterableExtensions.excludeAt","href":"darq/InsertionIterableExtensions/excludeAt.html","type":"method","overriddenDepth":0,"enclosedBy":{"name":"InsertionIterableExtensions","type":"extension"}},{"name":"excludeRange","qualifiedName":"darq.InsertionIterableExtensions.excludeRange","href":"darq/InsertionIterableExtensions/excludeRange.html","type":"method","overriddenDepth":0,"enclosedBy":{"name":"InsertionIterableExtensions","type":"extension"}},{"name":"insert","qualifiedName":"darq.InsertionIterableExtensions.insert","href":"darq/InsertionIterableExtensions/insert.html","type":"method","overriddenDepth":0,"enclosedBy":{"name":"InsertionIterableExtensions","type":"extension"}},{"name":"insert2","qualifiedName":"darq.InsertionIterableExtensions.insert2","href":"darq/InsertionIterableExtensions/insert2.html","type":"method","overriddenDepth":0,"enclosedBy":{"name":"InsertionIterableExtensions","type":"extension"}},{"name":"insert3","qualifiedName":"darq.InsertionIterableExtensions.insert3","href":"darq/InsertionIterableExtensions/insert3.html","type":"method","overriddenDepth":0,"enclosedBy":{"name":"InsertionIterableExtensions","type":"extension"}},{"name":"insert4","qualifiedName":"darq.InsertionIterableExtensions.insert4","href":"darq/InsertionIterableExtensions/insert4.html","type":"method","overriddenDepth":0,"enclosedBy":{"name":"InsertionIterableExtensions","type":"extension"}},{"name":"insert5","qualifiedName":"darq.InsertionIterableExtensions.insert5","href":"darq/InsertionIterableExtensions/insert5.html","type":"method","overriddenDepth":0,"enclosedBy":{"name":"InsertionIterableExtensions","type":"extension"}},{"name":"insert6","qualifiedName":"darq.InsertionIterableExtensions.insert6","href":"darq/InsertionIterableExtensions/insert6.html","type":"method","overriddenDepth":0,"enclosedBy":{"name":"InsertionIterableExtensions","type":"extension"}},{"name":"insert7","qualifiedName":"darq.InsertionIterableExtensions.insert7","href":"darq/InsertionIterableExtensions/insert7.html","type":"method","overriddenDepth":0,"enclosedBy":{"name":"InsertionIterableExtensions","type":"extension"}},{"name":"insert8","qualifiedName":"darq.InsertionIterableExtensions.insert8","href":"darq/InsertionIterableExtensions/insert8.html","type":"method","overriddenDepth":0,"enclosedBy":{"name":"InsertionIterableExtensions","type":"extension"}},{"name":"insert9","qualifiedName":"darq.InsertionIterableExtensions.insert9","href":"darq/InsertionIterableExtensions/insert9.html","type":"method","overriddenDepth":0,"enclosedBy":{"name":"InsertionIterableExtensions","type":"extension"}},{"name":"insertAll","qualifiedName":"darq.InsertionIterableExtensions.insertAll","href":"darq/InsertionIterableExtensions/insertAll.html","type":"method","overriddenDepth":0,"enclosedBy":{"name":"InsertionIterableExtensions","type":"extension"}},{"name":"insertOrAppend","qualifiedName":"darq.InsertionIterableExtensions.insertOrAppend","href":"darq/InsertionIterableExtensions/insertOrAppend.html","type":"method","overriddenDepth":0,"enclosedBy":{"name":"InsertionIterableExtensions","type":"extension"}},{"name":"insertOrAppend2","qualifiedName":"darq.InsertionIterableExtensions.insertOrAppend2","href":"darq/InsertionIterableExtensions/insertOrAppend2.html","type":"method","overriddenDepth":0,"enclosedBy":{"name":"InsertionIterableExtensions","type":"extension"}},{"name":"insertOrAppend3","qualifiedName":"darq.InsertionIterableExtensions.insertOrAppend3","href":"darq/InsertionIterableExtensions/insertOrAppend3.html","type":"method","overriddenDepth":0,"enclosedBy":{"name":"InsertionIterableExtensions","type":"extension"}},{"name":"insertOrAppend4","qualifiedName":"darq.InsertionIterableExtensions.insertOrAppend4","href":"darq/InsertionIterableExtensions/insertOrAppend4.html","type":"method","overriddenDepth":0,"enclosedBy":{"name":"InsertionIterableExtensions","type":"extension"}},{"name":"insertOrAppend5","qualifiedName":"darq.InsertionIterableExtensions.insertOrAppend5","href":"darq/InsertionIterableExtensions/insertOrAppend5.html","type":"method","overriddenDepth":0,"enclosedBy":{"name":"InsertionIterableExtensions","type":"extension"}},{"name":"insertOrAppend6","qualifiedName":"darq.InsertionIterableExtensions.insertOrAppend6","href":"darq/InsertionIterableExtensions/insertOrAppend6.html","type":"method","overriddenDepth":0,"enclosedBy":{"name":"InsertionIterableExtensions","type":"extension"}},{"name":"insertOrAppend7","qualifiedName":"darq.InsertionIterableExtensions.insertOrAppend7","href":"darq/InsertionIterableExtensions/insertOrAppend7.html","type":"method","overriddenDepth":0,"enclosedBy":{"name":"InsertionIterableExtensions","type":"extension"}},{"name":"insertOrAppend8","qualifiedName":"darq.InsertionIterableExtensions.insertOrAppend8","href":"darq/InsertionIterableExtensions/insertOrAppend8.html","type":"method","overriddenDepth":0,"enclosedBy":{"name":"InsertionIterableExtensions","type":"extension"}},{"name":"insertOrAppend9","qualifiedName":"darq.InsertionIterableExtensions.insertOrAppend9","href":"darq/InsertionIterableExtensions/insertOrAppend9.html","type":"method","overriddenDepth":0,"enclosedBy":{"name":"InsertionIterableExtensions","type":"extension"}},{"name":"insertOrAppendAll","qualifiedName":"darq.InsertionIterableExtensions.insertOrAppendAll","href":"darq/InsertionIterableExtensions/insertOrAppendAll.html","type":"method","overriddenDepth":0,"enclosedBy":{"name":"InsertionIterableExtensions","type":"extension"}},{"name":"padEnd","qualifiedName":"darq.InsertionIterableExtensions.padEnd","href":"darq/InsertionIterableExtensions/padEnd.html","type":"method","overriddenDepth":0,"enclosedBy":{"name":"InsertionIterableExtensions","type":"extension"}},{"name":"padStart","qualifiedName":"darq.InsertionIterableExtensions.padStart","href":"darq/InsertionIterableExtensions/padStart.html","type":"method","overriddenDepth":0,"enclosedBy":{"name":"InsertionIterableExtensions","type":"extension"}},{"name":"prepend","qualifiedName":"darq.InsertionIterableExtensions.prepend","href":"darq/InsertionIterableExtensions/prepend.html","type":"method","overriddenDepth":0,"enclosedBy":{"name":"InsertionIterableExtensions","type":"extension"}},{"name":"prepend2","qualifiedName":"darq.InsertionIterableExtensions.prepend2","href":"darq/InsertionIterableExtensions/prepend2.html","type":"method","overriddenDepth":0,"enclosedBy":{"name":"InsertionIterableExtensions","type":"extension"}},{"name":"prepend3","qualifiedName":"darq.InsertionIterableExtensions.prepend3","href":"darq/InsertionIterableExtensions/prepend3.html","type":"method","overriddenDepth":0,"enclosedBy":{"name":"InsertionIterableExtensions","type":"extension"}},{"name":"prepend4","qualifiedName":"darq.InsertionIterableExtensions.prepend4","href":"darq/InsertionIterableExtensions/prepend4.html","type":"method","overriddenDepth":0,"enclosedBy":{"name":"InsertionIterableExtensions","type":"extension"}},{"name":"prepend5","qualifiedName":"darq.InsertionIterableExtensions.prepend5","href":"darq/InsertionIterableExtensions/prepend5.html","type":"method","overriddenDepth":0,"enclosedBy":{"name":"InsertionIterableExtensions","type":"extension"}},{"name":"prepend6","qualifiedName":"darq.InsertionIterableExtensions.prepend6","href":"darq/InsertionIterableExtensions/prepend6.html","type":"method","overriddenDepth":0,"enclosedBy":{"name":"InsertionIterableExtensions","type":"extension"}},{"name":"prepend7","qualifiedName":"darq.InsertionIterableExtensions.prepend7","href":"darq/InsertionIterableExtensions/prepend7.html","type":"method","overriddenDepth":0,"enclosedBy":{"name":"InsertionIterableExtensions","type":"extension"}},{"name":"prepend8","qualifiedName":"darq.InsertionIterableExtensions.prepend8","href":"darq/InsertionIterableExtensions/prepend8.html","type":"method","overriddenDepth":0,"enclosedBy":{"name":"InsertionIterableExtensions","type":"extension"}},{"name":"prepend9","qualifiedName":"darq.InsertionIterableExtensions.prepend9","href":"darq/InsertionIterableExtensions/prepend9.html","type":"method","overriddenDepth":0,"enclosedBy":{"name":"InsertionIterableExtensions","type":"extension"}},{"name":"prependAll","qualifiedName":"darq.InsertionIterableExtensions.prependAll","href":"darq/InsertionIterableExtensions/prependAll.html","type":"method","overriddenDepth":0,"enclosedBy":{"name":"InsertionIterableExtensions","type":"extension"}},{"name":"tryInsert","qualifiedName":"darq.InsertionIterableExtensions.tryInsert","href":"darq/InsertionIterableExtensions/tryInsert.html","type":"method","overriddenDepth":0,"enclosedBy":{"name":"InsertionIterableExtensions","type":"extension"}},{"name":"tryInsert2","qualifiedName":"darq.InsertionIterableExtensions.tryInsert2","href":"darq/InsertionIterableExtensions/tryInsert2.html","type":"method","overriddenDepth":0,"enclosedBy":{"name":"InsertionIterableExtensions","type":"extension"}},{"name":"tryInsert3","qualifiedName":"darq.InsertionIterableExtensions.tryInsert3","href":"darq/InsertionIterableExtensions/tryInsert3.html","type":"method","overriddenDepth":0,"enclosedBy":{"name":"InsertionIterableExtensions","type":"extension"}},{"name":"tryInsert4","qualifiedName":"darq.InsertionIterableExtensions.tryInsert4","href":"darq/InsertionIterableExtensions/tryInsert4.html","type":"method","overriddenDepth":0,"enclosedBy":{"name":"InsertionIterableExtensions","type":"extension"}},{"name":"tryInsert5","qualifiedName":"darq.InsertionIterableExtensions.tryInsert5","href":"darq/InsertionIterableExtensions/tryInsert5.html","type":"method","overriddenDepth":0,"enclosedBy":{"name":"InsertionIterableExtensions","type":"extension"}},{"name":"tryInsert6","qualifiedName":"darq.InsertionIterableExtensions.tryInsert6","href":"darq/InsertionIterableExtensions/tryInsert6.html","type":"method","overriddenDepth":0,"enclosedBy":{"name":"InsertionIterableExtensions","type":"extension"}},{"name":"tryInsert7","qualifiedName":"darq.InsertionIterableExtensions.tryInsert7","href":"darq/InsertionIterableExtensions/tryInsert7.html","type":"method","overriddenDepth":0,"enclosedBy":{"name":"InsertionIterableExtensions","type":"extension"}},{"name":"tryInsert8","qualifiedName":"darq.InsertionIterableExtensions.tryInsert8","href":"darq/InsertionIterableExtensions/tryInsert8.html","type":"method","overriddenDepth":0,"enclosedBy":{"name":"InsertionIterableExtensions","type":"extension"}},{"name":"tryInsert9","qualifiedName":"darq.InsertionIterableExtensions.tryInsert9","href":"darq/InsertionIterableExtensions/tryInsert9.html","type":"method","overriddenDepth":0,"enclosedBy":{"name":"InsertionIterableExtensions","type":"extension"}},{"name":"tryInsertAll","qualifiedName":"darq.InsertionIterableExtensions.tryInsertAll","href":"darq/InsertionIterableExtensions/tryInsertAll.html","type":"method","overriddenDepth":0,"enclosedBy":{"name":"InsertionIterableExtensions","type":"extension"}},{"name":"MathConsumerExtensions","qualifiedName":"darq.MathConsumerExtensions","href":"darq/MathConsumerExtensions.html","type":"extension","overriddenDepth":0,"enclosedBy":{"name":"darq","type":"library"}},{"name":"aggregate","qualifiedName":"darq.MathConsumerExtensions.aggregate","href":"darq/MathConsumerExtensions/aggregate.html","type":"method","overriddenDepth":0,"enclosedBy":{"name":"MathConsumerExtensions","type":"extension"}},{"name":"aggregateRight","qualifiedName":"darq.MathConsumerExtensions.aggregateRight","href":"darq/MathConsumerExtensions/aggregateRight.html","type":"method","overriddenDepth":0,"enclosedBy":{"name":"MathConsumerExtensions","type":"extension"}},{"name":"average","qualifiedName":"darq.MathConsumerExtensions.average","href":"darq/MathConsumerExtensions/average.html","type":"method","overriddenDepth":0,"enclosedBy":{"name":"MathConsumerExtensions","type":"extension"}},{"name":"count","qualifiedName":"darq.MathConsumerExtensions.count","href":"darq/MathConsumerExtensions/count.html","type":"method","overriddenDepth":0,"enclosedBy":{"name":"MathConsumerExtensions","type":"extension"}},{"name":"countBy","qualifiedName":"darq.MathConsumerExtensions.countBy","href":"darq/MathConsumerExtensions/countBy.html","type":"method","overriddenDepth":0,"enclosedBy":{"name":"MathConsumerExtensions","type":"extension"}},{"name":"max","qualifiedName":"darq.MathConsumerExtensions.max","href":"darq/MathConsumerExtensions/max.html","type":"method","overriddenDepth":0,"enclosedBy":{"name":"MathConsumerExtensions","type":"extension"}},{"name":"min","qualifiedName":"darq.MathConsumerExtensions.min","href":"darq/MathConsumerExtensions/min.html","type":"method","overriddenDepth":0,"enclosedBy":{"name":"MathConsumerExtensions","type":"extension"}},{"name":"sum","qualifiedName":"darq.MathConsumerExtensions.sum","href":"darq/MathConsumerExtensions/sum.html","type":"method","overriddenDepth":0,"enclosedBy":{"name":"MathConsumerExtensions","type":"extension"}},{"name":"MutationIterableExtensions","qualifiedName":"darq.MutationIterableExtensions","href":"darq/MutationIterableExtensions.html","type":"extension","overriddenDepth":0,"enclosedBy":{"name":"darq","type":"library"}},{"name":"fillBackward","qualifiedName":"darq.MutationIterableExtensions.fillBackward","href":"darq/MutationIterableExtensions/fillBackward.html","type":"method","overriddenDepth":0,"enclosedBy":{"name":"MutationIterableExtensions","type":"extension"}},{"name":"fillForward","qualifiedName":"darq.MutationIterableExtensions.fillForward","href":"darq/MutationIterableExtensions/fillForward.html","type":"method","overriddenDepth":0,"enclosedBy":{"name":"MutationIterableExtensions","type":"extension"}},{"name":"fillMissing","qualifiedName":"darq.MutationIterableExtensions.fillMissing","href":"darq/MutationIterableExtensions/fillMissing.html","type":"method","overriddenDepth":0,"enclosedBy":{"name":"MutationIterableExtensions","type":"extension"}},{"name":"flatten","qualifiedName":"darq.MutationIterableExtensions.flatten","href":"darq/MutationIterableExtensions/flatten.html","type":"method","overriddenDepth":0,"enclosedBy":{"name":"MutationIterableExtensions","type":"extension"}},{"name":"index","qualifiedName":"darq.MutationIterableExtensions.index","href":"darq/MutationIterableExtensions/index.html","type":"method","overriddenDepth":0,"enclosedBy":{"name":"MutationIterableExtensions","type":"extension"}},{"name":"interleave","qualifiedName":"darq.MutationIterableExtensions.interleave","href":"darq/MutationIterableExtensions/interleave.html","type":"method","overriddenDepth":0,"enclosedBy":{"name":"MutationIterableExtensions","type":"extension"}},{"name":"interleaveAll","qualifiedName":"darq.MutationIterableExtensions.interleaveAll","href":"darq/MutationIterableExtensions/interleaveAll.html","type":"method","overriddenDepth":0,"enclosedBy":{"name":"MutationIterableExtensions","type":"extension"}},{"name":"joinMap","qualifiedName":"darq.MutationIterableExtensions.joinMap","href":"darq/MutationIterableExtensions/joinMap.html","type":"method","overriddenDepth":0,"enclosedBy":{"name":"MutationIterableExtensions","type":"extension"}},{"name":"lag","qualifiedName":"darq.MutationIterableExtensions.lag","href":"darq/MutationIterableExtensions/lag.html","type":"method","overriddenDepth":0,"enclosedBy":{"name":"MutationIterableExtensions","type":"extension"}},{"name":"lead","qualifiedName":"darq.MutationIterableExtensions.lead","href":"darq/MutationIterableExtensions/lead.html","type":"method","overriddenDepth":0,"enclosedBy":{"name":"MutationIterableExtensions","type":"extension"}},{"name":"move","qualifiedName":"darq.MutationIterableExtensions.move","href":"darq/MutationIterableExtensions/move.html","type":"method","overriddenDepth":0,"enclosedBy":{"name":"MutationIterableExtensions","type":"extension"}},{"name":"nonNull","qualifiedName":"darq.MutationIterableExtensions.nonNull","href":"darq/MutationIterableExtensions/nonNull.html","type":"method","overriddenDepth":0,"enclosedBy":{"name":"MutationIterableExtensions","type":"extension"}},{"name":"ofType","qualifiedName":"darq.MutationIterableExtensions.ofType","href":"darq/MutationIterableExtensions/ofType.html","type":"method","overriddenDepth":0,"enclosedBy":{"name":"MutationIterableExtensions","type":"extension"}},{"name":"ofType2","qualifiedName":"darq.MutationIterableExtensions.ofType2","href":"darq/MutationIterableExtensions/ofType2.html","type":"method","overriddenDepth":0,"enclosedBy":{"name":"MutationIterableExtensions","type":"extension"}},{"name":"ofType3","qualifiedName":"darq.MutationIterableExtensions.ofType3","href":"darq/MutationIterableExtensions/ofType3.html","type":"method","overriddenDepth":0,"enclosedBy":{"name":"MutationIterableExtensions","type":"extension"}},{"name":"ofType4","qualifiedName":"darq.MutationIterableExtensions.ofType4","href":"darq/MutationIterableExtensions/ofType4.html","type":"method","overriddenDepth":0,"enclosedBy":{"name":"MutationIterableExtensions","type":"extension"}},{"name":"ofType5","qualifiedName":"darq.MutationIterableExtensions.ofType5","href":"darq/MutationIterableExtensions/ofType5.html","type":"method","overriddenDepth":0,"enclosedBy":{"name":"MutationIterableExtensions","type":"extension"}},{"name":"ofType6","qualifiedName":"darq.MutationIterableExtensions.ofType6","href":"darq/MutationIterableExtensions/ofType6.html","type":"method","overriddenDepth":0,"enclosedBy":{"name":"MutationIterableExtensions","type":"extension"}},{"name":"ofType7","qualifiedName":"darq.MutationIterableExtensions.ofType7","href":"darq/MutationIterableExtensions/ofType7.html","type":"method","overriddenDepth":0,"enclosedBy":{"name":"MutationIterableExtensions","type":"extension"}},{"name":"ofType8","qualifiedName":"darq.MutationIterableExtensions.ofType8","href":"darq/MutationIterableExtensions/ofType8.html","type":"method","overriddenDepth":0,"enclosedBy":{"name":"MutationIterableExtensions","type":"extension"}},{"name":"ofType9","qualifiedName":"darq.MutationIterableExtensions.ofType9","href":"darq/MutationIterableExtensions/ofType9.html","type":"method","overriddenDepth":0,"enclosedBy":{"name":"MutationIterableExtensions","type":"extension"}},{"name":"prescan","qualifiedName":"darq.MutationIterableExtensions.prescan","href":"darq/MutationIterableExtensions/prescan.html","type":"method","overriddenDepth":0,"enclosedBy":{"name":"MutationIterableExtensions","type":"extension"}},{"name":"scan","qualifiedName":"darq.MutationIterableExtensions.scan","href":"darq/MutationIterableExtensions/scan.html","type":"method","overriddenDepth":0,"enclosedBy":{"name":"MutationIterableExtensions","type":"extension"}},{"name":"select","qualifiedName":"darq.MutationIterableExtensions.select","href":"darq/MutationIterableExtensions/select.html","type":"method","overriddenDepth":0,"enclosedBy":{"name":"MutationIterableExtensions","type":"extension"}},{"name":"selectMany","qualifiedName":"darq.MutationIterableExtensions.selectMany","href":"darq/MutationIterableExtensions/selectMany.html","type":"method","overriddenDepth":0,"enclosedBy":{"name":"MutationIterableExtensions","type":"extension"}},{"name":"zip","qualifiedName":"darq.MutationIterableExtensions.zip","href":"darq/MutationIterableExtensions/zip.html","type":"method","overriddenDepth":0,"enclosedBy":{"name":"MutationIterableExtensions","type":"extension"}},{"name":"OrderedIterableExtensions","qualifiedName":"darq.OrderedIterableExtensions","href":"darq/OrderedIterableExtensions.html","type":"extension","overriddenDepth":0,"enclosedBy":{"name":"darq","type":"library"}},{"name":"orderBy","qualifiedName":"darq.OrderedIterableExtensions.orderBy","href":"darq/OrderedIterableExtensions/orderBy.html","type":"method","overriddenDepth":0,"enclosedBy":{"name":"OrderedIterableExtensions","type":"extension"}},{"name":"orderByDescending","qualifiedName":"darq.OrderedIterableExtensions.orderByDescending","href":"darq/OrderedIterableExtensions/orderByDescending.html","type":"method","overriddenDepth":0,"enclosedBy":{"name":"OrderedIterableExtensions","type":"extension"}},{"name":"reverse","qualifiedName":"darq.OrderedIterableExtensions.reverse","href":"darq/OrderedIterableExtensions/reverse.html","type":"method","overriddenDepth":0,"enclosedBy":{"name":"OrderedIterableExtensions","type":"extension"}},{"name":"thenBy","qualifiedName":"darq.OrderedIterableExtensions.thenBy","href":"darq/OrderedIterableExtensions/thenBy.html","type":"method","overriddenDepth":0,"enclosedBy":{"name":"OrderedIterableExtensions","type":"extension"}},{"name":"thenByDescending","qualifiedName":"darq.OrderedIterableExtensions.thenByDescending","href":"darq/OrderedIterableExtensions/thenByDescending.html","type":"method","overriddenDepth":0,"enclosedBy":{"name":"OrderedIterableExtensions","type":"extension"}},{"name":"OtherConsumerExtensions","qualifiedName":"darq.OtherConsumerExtensions","href":"darq/OtherConsumerExtensions.html","type":"extension","overriddenDepth":0,"enclosedBy":{"name":"darq","type":"library"}},{"name":"consume","qualifiedName":"darq.OtherConsumerExtensions.consume","href":"darq/OtherConsumerExtensions/consume.html","type":"method","overriddenDepth":0,"enclosedBy":{"name":"OtherConsumerExtensions","type":"extension"}},{"name":"OtherIterableExtensions","qualifiedName":"darq.OtherIterableExtensions","href":"darq/OtherIterableExtensions.html","type":"extension","overriddenDepth":0,"enclosedBy":{"name":"darq","type":"library"}},{"name":"memoize","qualifiedName":"darq.OtherIterableExtensions.memoize","href":"darq/OtherIterableExtensions/memoize.html","type":"method","overriddenDepth":0,"enclosedBy":{"name":"OtherIterableExtensions","type":"extension"}},{"name":"randomSubset","qualifiedName":"darq.OtherIterableExtensions.randomSubset","href":"darq/OtherIterableExtensions/randomSubset.html","type":"method","overriddenDepth":0,"enclosedBy":{"name":"OtherIterableExtensions","type":"extension"}},{"name":"repeat","qualifiedName":"darq.OtherIterableExtensions.repeat","href":"darq/OtherIterableExtensions/repeat.html","type":"method","overriddenDepth":0,"enclosedBy":{"name":"OtherIterableExtensions","type":"extension"}},{"name":"skipLast","qualifiedName":"darq.OtherIterableExtensions.skipLast","href":"darq/OtherIterableExtensions/skipLast.html","type":"method","overriddenDepth":0,"enclosedBy":{"name":"OtherIterableExtensions","type":"extension"}},{"name":"split","qualifiedName":"darq.OtherIterableExtensions.split","href":"darq/OtherIterableExtensions/split.html","type":"method","overriddenDepth":0,"enclosedBy":{"name":"OtherIterableExtensions","type":"extension"}},{"name":"takeEvery","qualifiedName":"darq.OtherIterableExtensions.takeEvery","href":"darq/OtherIterableExtensions/takeEvery.html","type":"method","overriddenDepth":0,"enclosedBy":{"name":"OtherIterableExtensions","type":"extension"}},{"name":"takeLast","qualifiedName":"darq.OtherIterableExtensions.takeLast","href":"darq/OtherIterableExtensions/takeLast.html","type":"method","overriddenDepth":0,"enclosedBy":{"name":"OtherIterableExtensions","type":"extension"}},{"name":"RangeIterable","qualifiedName":"darq.RangeIterable","href":"darq/RangeIterable-class.html","type":"class","overriddenDepth":0,"enclosedBy":{"name":"darq","type":"library"}},{"name":"operator ==","qualifiedName":"darq.RangeIterable.==","href":"darq/RangeIterable/operator_equals.html","type":"method","overriddenDepth":0,"enclosedBy":{"name":"RangeIterable","type":"class"}},{"name":"RangeIterable","qualifiedName":"darq.RangeIterable.RangeIterable","href":"darq/RangeIterable/RangeIterable.html","type":"constructor","overriddenDepth":0,"enclosedBy":{"name":"RangeIterable","type":"class"}},{"name":"any","qualifiedName":"darq.RangeIterable.any","href":"darq/RangeIterable/any.html","type":"method","overriddenDepth":0,"enclosedBy":{"name":"RangeIterable","type":"class"}},{"name":"cast","qualifiedName":"darq.RangeIterable.cast","href":"darq/RangeIterable/cast.html","type":"method","overriddenDepth":0,"enclosedBy":{"name":"RangeIterable","type":"class"}},{"name":"contains","qualifiedName":"darq.RangeIterable.contains","href":"darq/RangeIterable/contains.html","type":"method","overriddenDepth":0,"enclosedBy":{"name":"RangeIterable","type":"class"}},{"name":"RangeIterable.count","qualifiedName":"darq.RangeIterable.count","href":"darq/RangeIterable/RangeIterable.count.html","type":"constructor","overriddenDepth":0,"enclosedBy":{"name":"RangeIterable","type":"class"}},{"name":"elementAt","qualifiedName":"darq.RangeIterable.elementAt","href":"darq/RangeIterable/elementAt.html","type":"method","overriddenDepth":0,"enclosedBy":{"name":"RangeIterable","type":"class"}},{"name":"end","qualifiedName":"darq.RangeIterable.end","href":"darq/RangeIterable/end.html","type":"property","overriddenDepth":0,"enclosedBy":{"name":"RangeIterable","type":"class"}},{"name":"every","qualifiedName":"darq.RangeIterable.every","href":"darq/RangeIterable/every.html","type":"method","overriddenDepth":0,"enclosedBy":{"name":"RangeIterable","type":"class"}},{"name":"expand","qualifiedName":"darq.RangeIterable.expand","href":"darq/RangeIterable/expand.html","type":"method","overriddenDepth":0,"enclosedBy":{"name":"RangeIterable","type":"class"}},{"name":"first","qualifiedName":"darq.RangeIterable.first","href":"darq/RangeIterable/first.html","type":"property","overriddenDepth":0,"enclosedBy":{"name":"RangeIterable","type":"class"}},{"name":"firstWhere","qualifiedName":"darq.RangeIterable.firstWhere","href":"darq/RangeIterable/firstWhere.html","type":"method","overriddenDepth":0,"enclosedBy":{"name":"RangeIterable","type":"class"}},{"name":"fold","qualifiedName":"darq.RangeIterable.fold","href":"darq/RangeIterable/fold.html","type":"method","overriddenDepth":0,"enclosedBy":{"name":"RangeIterable","type":"class"}},{"name":"followedBy","qualifiedName":"darq.RangeIterable.followedBy","href":"darq/RangeIterable/followedBy.html","type":"method","overriddenDepth":0,"enclosedBy":{"name":"RangeIterable","type":"class"}},{"name":"forEach","qualifiedName":"darq.RangeIterable.forEach","href":"darq/RangeIterable/forEach.html","type":"method","overriddenDepth":0,"enclosedBy":{"name":"RangeIterable","type":"class"}},{"name":"hashCode","qualifiedName":"darq.RangeIterable.hashCode","href":"darq/RangeIterable/hashCode.html","type":"property","overriddenDepth":0,"enclosedBy":{"name":"RangeIterable","type":"class"}},{"name":"interval","qualifiedName":"darq.RangeIterable.interval","href":"darq/RangeIterable/interval.html","type":"property","overriddenDepth":0,"enclosedBy":{"name":"RangeIterable","type":"class"}},{"name":"isEmpty","qualifiedName":"darq.RangeIterable.isEmpty","href":"darq/RangeIterable/isEmpty.html","type":"property","overriddenDepth":0,"enclosedBy":{"name":"RangeIterable","type":"class"}},{"name":"isNotEmpty","qualifiedName":"darq.RangeIterable.isNotEmpty","href":"darq/RangeIterable/isNotEmpty.html","type":"property","overriddenDepth":0,"enclosedBy":{"name":"RangeIterable","type":"class"}},{"name":"iterator","qualifiedName":"darq.RangeIterable.iterator","href":"darq/RangeIterable/iterator.html","type":"property","overriddenDepth":0,"enclosedBy":{"name":"RangeIterable","type":"class"}},{"name":"join","qualifiedName":"darq.RangeIterable.join","href":"darq/RangeIterable/join.html","type":"method","overriddenDepth":0,"enclosedBy":{"name":"RangeIterable","type":"class"}},{"name":"last","qualifiedName":"darq.RangeIterable.last","href":"darq/RangeIterable/last.html","type":"property","overriddenDepth":0,"enclosedBy":{"name":"RangeIterable","type":"class"}},{"name":"lastWhere","qualifiedName":"darq.RangeIterable.lastWhere","href":"darq/RangeIterable/lastWhere.html","type":"method","overriddenDepth":0,"enclosedBy":{"name":"RangeIterable","type":"class"}},{"name":"length","qualifiedName":"darq.RangeIterable.length","href":"darq/RangeIterable/length.html","type":"property","overriddenDepth":0,"enclosedBy":{"name":"RangeIterable","type":"class"}},{"name":"map","qualifiedName":"darq.RangeIterable.map","href":"darq/RangeIterable/map.html","type":"method","overriddenDepth":0,"enclosedBy":{"name":"RangeIterable","type":"class"}},{"name":"noSuchMethod","qualifiedName":"darq.RangeIterable.noSuchMethod","href":"darq/RangeIterable/noSuchMethod.html","type":"method","overriddenDepth":0,"enclosedBy":{"name":"RangeIterable","type":"class"}},{"name":"reduce","qualifiedName":"darq.RangeIterable.reduce","href":"darq/RangeIterable/reduce.html","type":"method","overriddenDepth":0,"enclosedBy":{"name":"RangeIterable","type":"class"}},{"name":"runtimeType","qualifiedName":"darq.RangeIterable.runtimeType","href":"darq/RangeIterable/runtimeType.html","type":"property","overriddenDepth":0,"enclosedBy":{"name":"RangeIterable","type":"class"}},{"name":"single","qualifiedName":"darq.RangeIterable.single","href":"darq/RangeIterable/single.html","type":"property","overriddenDepth":0,"enclosedBy":{"name":"RangeIterable","type":"class"}},{"name":"singleWhere","qualifiedName":"darq.RangeIterable.singleWhere","href":"darq/RangeIterable/singleWhere.html","type":"method","overriddenDepth":0,"enclosedBy":{"name":"RangeIterable","type":"class"}},{"name":"skip","qualifiedName":"darq.RangeIterable.skip","href":"darq/RangeIterable/skip.html","type":"method","overriddenDepth":0,"enclosedBy":{"name":"RangeIterable","type":"class"}},{"name":"skipWhile","qualifiedName":"darq.RangeIterable.skipWhile","href":"darq/RangeIterable/skipWhile.html","type":"method","overriddenDepth":0,"enclosedBy":{"name":"RangeIterable","type":"class"}},{"name":"start","qualifiedName":"darq.RangeIterable.start","href":"darq/RangeIterable/start.html","type":"property","overriddenDepth":0,"enclosedBy":{"name":"RangeIterable","type":"class"}},{"name":"take","qualifiedName":"darq.RangeIterable.take","href":"darq/RangeIterable/take.html","type":"method","overriddenDepth":0,"enclosedBy":{"name":"RangeIterable","type":"class"}},{"name":"takeWhile","qualifiedName":"darq.RangeIterable.takeWhile","href":"darq/RangeIterable/takeWhile.html","type":"method","overriddenDepth":0,"enclosedBy":{"name":"RangeIterable","type":"class"}},{"name":"toList","qualifiedName":"darq.RangeIterable.toList","href":"darq/RangeIterable/toList.html","type":"method","overriddenDepth":0,"enclosedBy":{"name":"RangeIterable","type":"class"}},{"name":"toSet","qualifiedName":"darq.RangeIterable.toSet","href":"darq/RangeIterable/toSet.html","type":"method","overriddenDepth":0,"enclosedBy":{"name":"RangeIterable","type":"class"}},{"name":"toString","qualifiedName":"darq.RangeIterable.toString","href":"darq/RangeIterable/toString.html","type":"method","overriddenDepth":1,"enclosedBy":{"name":"RangeIterable","type":"class"}},{"name":"where","qualifiedName":"darq.RangeIterable.where","href":"darq/RangeIterable/where.html","type":"method","overriddenDepth":0,"enclosedBy":{"name":"RangeIterable","type":"class"}},{"name":"whereType","qualifiedName":"darq.RangeIterable.whereType","href":"darq/RangeIterable/whereType.html","type":"method","overriddenDepth":0,"enclosedBy":{"name":"RangeIterable","type":"class"}},{"name":"RepeatIterable","qualifiedName":"darq.RepeatIterable","href":"darq/RepeatIterable-class.html","type":"class","overriddenDepth":0,"enclosedBy":{"name":"darq","type":"library"}},{"name":"operator ==","qualifiedName":"darq.RepeatIterable.==","href":"darq/RepeatIterable/operator_equals.html","type":"method","overriddenDepth":0,"enclosedBy":{"name":"RepeatIterable","type":"class"}},{"name":"RepeatIterable","qualifiedName":"darq.RepeatIterable.RepeatIterable","href":"darq/RepeatIterable/RepeatIterable.html","type":"constructor","overriddenDepth":0,"enclosedBy":{"name":"RepeatIterable","type":"class"}},{"name":"any","qualifiedName":"darq.RepeatIterable.any","href":"darq/RepeatIterable/any.html","type":"method","overriddenDepth":0,"enclosedBy":{"name":"RepeatIterable","type":"class"}},{"name":"cast","qualifiedName":"darq.RepeatIterable.cast","href":"darq/RepeatIterable/cast.html","type":"method","overriddenDepth":0,"enclosedBy":{"name":"RepeatIterable","type":"class"}},{"name":"contains","qualifiedName":"darq.RepeatIterable.contains","href":"darq/RepeatIterable/contains.html","type":"method","overriddenDepth":0,"enclosedBy":{"name":"RepeatIterable","type":"class"}},{"name":"count","qualifiedName":"darq.RepeatIterable.count","href":"darq/RepeatIterable/count.html","type":"property","overriddenDepth":0,"enclosedBy":{"name":"RepeatIterable","type":"class"}},{"name":"element","qualifiedName":"darq.RepeatIterable.element","href":"darq/RepeatIterable/element.html","type":"property","overriddenDepth":0,"enclosedBy":{"name":"RepeatIterable","type":"class"}},{"name":"elementAt","qualifiedName":"darq.RepeatIterable.elementAt","href":"darq/RepeatIterable/elementAt.html","type":"method","overriddenDepth":0,"enclosedBy":{"name":"RepeatIterable","type":"class"}},{"name":"every","qualifiedName":"darq.RepeatIterable.every","href":"darq/RepeatIterable/every.html","type":"method","overriddenDepth":0,"enclosedBy":{"name":"RepeatIterable","type":"class"}},{"name":"expand","qualifiedName":"darq.RepeatIterable.expand","href":"darq/RepeatIterable/expand.html","type":"method","overriddenDepth":0,"enclosedBy":{"name":"RepeatIterable","type":"class"}},{"name":"first","qualifiedName":"darq.RepeatIterable.first","href":"darq/RepeatIterable/first.html","type":"property","overriddenDepth":0,"enclosedBy":{"name":"RepeatIterable","type":"class"}},{"name":"firstWhere","qualifiedName":"darq.RepeatIterable.firstWhere","href":"darq/RepeatIterable/firstWhere.html","type":"method","overriddenDepth":0,"enclosedBy":{"name":"RepeatIterable","type":"class"}},{"name":"fold","qualifiedName":"darq.RepeatIterable.fold","href":"darq/RepeatIterable/fold.html","type":"method","overriddenDepth":0,"enclosedBy":{"name":"RepeatIterable","type":"class"}},{"name":"followedBy","qualifiedName":"darq.RepeatIterable.followedBy","href":"darq/RepeatIterable/followedBy.html","type":"method","overriddenDepth":0,"enclosedBy":{"name":"RepeatIterable","type":"class"}},{"name":"forEach","qualifiedName":"darq.RepeatIterable.forEach","href":"darq/RepeatIterable/forEach.html","type":"method","overriddenDepth":0,"enclosedBy":{"name":"RepeatIterable","type":"class"}},{"name":"hashCode","qualifiedName":"darq.RepeatIterable.hashCode","href":"darq/RepeatIterable/hashCode.html","type":"property","overriddenDepth":0,"enclosedBy":{"name":"RepeatIterable","type":"class"}},{"name":"isEmpty","qualifiedName":"darq.RepeatIterable.isEmpty","href":"darq/RepeatIterable/isEmpty.html","type":"property","overriddenDepth":0,"enclosedBy":{"name":"RepeatIterable","type":"class"}},{"name":"isNotEmpty","qualifiedName":"darq.RepeatIterable.isNotEmpty","href":"darq/RepeatIterable/isNotEmpty.html","type":"property","overriddenDepth":0,"enclosedBy":{"name":"RepeatIterable","type":"class"}},{"name":"iterator","qualifiedName":"darq.RepeatIterable.iterator","href":"darq/RepeatIterable/iterator.html","type":"property","overriddenDepth":0,"enclosedBy":{"name":"RepeatIterable","type":"class"}},{"name":"join","qualifiedName":"darq.RepeatIterable.join","href":"darq/RepeatIterable/join.html","type":"method","overriddenDepth":0,"enclosedBy":{"name":"RepeatIterable","type":"class"}},{"name":"last","qualifiedName":"darq.RepeatIterable.last","href":"darq/RepeatIterable/last.html","type":"property","overriddenDepth":0,"enclosedBy":{"name":"RepeatIterable","type":"class"}},{"name":"lastWhere","qualifiedName":"darq.RepeatIterable.lastWhere","href":"darq/RepeatIterable/lastWhere.html","type":"method","overriddenDepth":0,"enclosedBy":{"name":"RepeatIterable","type":"class"}},{"name":"length","qualifiedName":"darq.RepeatIterable.length","href":"darq/RepeatIterable/length.html","type":"property","overriddenDepth":0,"enclosedBy":{"name":"RepeatIterable","type":"class"}},{"name":"map","qualifiedName":"darq.RepeatIterable.map","href":"darq/RepeatIterable/map.html","type":"method","overriddenDepth":0,"enclosedBy":{"name":"RepeatIterable","type":"class"}},{"name":"noSuchMethod","qualifiedName":"darq.RepeatIterable.noSuchMethod","href":"darq/RepeatIterable/noSuchMethod.html","type":"method","overriddenDepth":0,"enclosedBy":{"name":"RepeatIterable","type":"class"}},{"name":"reduce","qualifiedName":"darq.RepeatIterable.reduce","href":"darq/RepeatIterable/reduce.html","type":"method","overriddenDepth":0,"enclosedBy":{"name":"RepeatIterable","type":"class"}},{"name":"runtimeType","qualifiedName":"darq.RepeatIterable.runtimeType","href":"darq/RepeatIterable/runtimeType.html","type":"property","overriddenDepth":0,"enclosedBy":{"name":"RepeatIterable","type":"class"}},{"name":"single","qualifiedName":"darq.RepeatIterable.single","href":"darq/RepeatIterable/single.html","type":"property","overriddenDepth":0,"enclosedBy":{"name":"RepeatIterable","type":"class"}},{"name":"singleWhere","qualifiedName":"darq.RepeatIterable.singleWhere","href":"darq/RepeatIterable/singleWhere.html","type":"method","overriddenDepth":0,"enclosedBy":{"name":"RepeatIterable","type":"class"}},{"name":"skip","qualifiedName":"darq.RepeatIterable.skip","href":"darq/RepeatIterable/skip.html","type":"method","overriddenDepth":0,"enclosedBy":{"name":"RepeatIterable","type":"class"}},{"name":"skipWhile","qualifiedName":"darq.RepeatIterable.skipWhile","href":"darq/RepeatIterable/skipWhile.html","type":"method","overriddenDepth":0,"enclosedBy":{"name":"RepeatIterable","type":"class"}},{"name":"take","qualifiedName":"darq.RepeatIterable.take","href":"darq/RepeatIterable/take.html","type":"method","overriddenDepth":0,"enclosedBy":{"name":"RepeatIterable","type":"class"}},{"name":"takeWhile","qualifiedName":"darq.RepeatIterable.takeWhile","href":"darq/RepeatIterable/takeWhile.html","type":"method","overriddenDepth":0,"enclosedBy":{"name":"RepeatIterable","type":"class"}},{"name":"toList","qualifiedName":"darq.RepeatIterable.toList","href":"darq/RepeatIterable/toList.html","type":"method","overriddenDepth":0,"enclosedBy":{"name":"RepeatIterable","type":"class"}},{"name":"toSet","qualifiedName":"darq.RepeatIterable.toSet","href":"darq/RepeatIterable/toSet.html","type":"method","overriddenDepth":0,"enclosedBy":{"name":"RepeatIterable","type":"class"}},{"name":"toString","qualifiedName":"darq.RepeatIterable.toString","href":"darq/RepeatIterable/toString.html","type":"method","overriddenDepth":1,"enclosedBy":{"name":"RepeatIterable","type":"class"}},{"name":"where","qualifiedName":"darq.RepeatIterable.where","href":"darq/RepeatIterable/where.html","type":"method","overriddenDepth":0,"enclosedBy":{"name":"RepeatIterable","type":"class"}},{"name":"whereType","qualifiedName":"darq.RepeatIterable.whereType","href":"darq/RepeatIterable/whereType.html","type":"method","overriddenDepth":0,"enclosedBy":{"name":"RepeatIterable","type":"class"}},{"name":"SetIterableExtensions","qualifiedName":"darq.SetIterableExtensions","href":"darq/SetIterableExtensions.html","type":"extension","overriddenDepth":0,"enclosedBy":{"name":"darq","type":"library"}},{"name":"cartesian","qualifiedName":"darq.SetIterableExtensions.cartesian","href":"darq/SetIterableExtensions/cartesian.html","type":"method","overriddenDepth":0,"enclosedBy":{"name":"SetIterableExtensions","type":"extension"}},{"name":"cartesian3","qualifiedName":"darq.SetIterableExtensions.cartesian3","href":"darq/SetIterableExtensions/cartesian3.html","type":"method","overriddenDepth":0,"enclosedBy":{"name":"SetIterableExtensions","type":"extension"}},{"name":"cartesian4","qualifiedName":"darq.SetIterableExtensions.cartesian4","href":"darq/SetIterableExtensions/cartesian4.html","type":"method","overriddenDepth":0,"enclosedBy":{"name":"SetIterableExtensions","type":"extension"}},{"name":"cartesian5","qualifiedName":"darq.SetIterableExtensions.cartesian5","href":"darq/SetIterableExtensions/cartesian5.html","type":"method","overriddenDepth":0,"enclosedBy":{"name":"SetIterableExtensions","type":"extension"}},{"name":"cartesian6","qualifiedName":"darq.SetIterableExtensions.cartesian6","href":"darq/SetIterableExtensions/cartesian6.html","type":"method","overriddenDepth":0,"enclosedBy":{"name":"SetIterableExtensions","type":"extension"}},{"name":"cartesian7","qualifiedName":"darq.SetIterableExtensions.cartesian7","href":"darq/SetIterableExtensions/cartesian7.html","type":"method","overriddenDepth":0,"enclosedBy":{"name":"SetIterableExtensions","type":"extension"}},{"name":"cartesian8","qualifiedName":"darq.SetIterableExtensions.cartesian8","href":"darq/SetIterableExtensions/cartesian8.html","type":"method","overriddenDepth":0,"enclosedBy":{"name":"SetIterableExtensions","type":"extension"}},{"name":"cartesian9","qualifiedName":"darq.SetIterableExtensions.cartesian9","href":"darq/SetIterableExtensions/cartesian9.html","type":"method","overriddenDepth":0,"enclosedBy":{"name":"SetIterableExtensions","type":"extension"}},{"name":"cartesianSelect","qualifiedName":"darq.SetIterableExtensions.cartesianSelect","href":"darq/SetIterableExtensions/cartesianSelect.html","type":"method","overriddenDepth":0,"enclosedBy":{"name":"SetIterableExtensions","type":"extension"}},{"name":"cartesianSelect3","qualifiedName":"darq.SetIterableExtensions.cartesianSelect3","href":"darq/SetIterableExtensions/cartesianSelect3.html","type":"method","overriddenDepth":0,"enclosedBy":{"name":"SetIterableExtensions","type":"extension"}},{"name":"cartesianSelect4","qualifiedName":"darq.SetIterableExtensions.cartesianSelect4","href":"darq/SetIterableExtensions/cartesianSelect4.html","type":"method","overriddenDepth":0,"enclosedBy":{"name":"SetIterableExtensions","type":"extension"}},{"name":"cartesianSelect5","qualifiedName":"darq.SetIterableExtensions.cartesianSelect5","href":"darq/SetIterableExtensions/cartesianSelect5.html","type":"method","overriddenDepth":0,"enclosedBy":{"name":"SetIterableExtensions","type":"extension"}},{"name":"cartesianSelect6","qualifiedName":"darq.SetIterableExtensions.cartesianSelect6","href":"darq/SetIterableExtensions/cartesianSelect6.html","type":"method","overriddenDepth":0,"enclosedBy":{"name":"SetIterableExtensions","type":"extension"}},{"name":"cartesianSelect7","qualifiedName":"darq.SetIterableExtensions.cartesianSelect7","href":"darq/SetIterableExtensions/cartesianSelect7.html","type":"method","overriddenDepth":0,"enclosedBy":{"name":"SetIterableExtensions","type":"extension"}},{"name":"cartesianSelect8","qualifiedName":"darq.SetIterableExtensions.cartesianSelect8","href":"darq/SetIterableExtensions/cartesianSelect8.html","type":"method","overriddenDepth":0,"enclosedBy":{"name":"SetIterableExtensions","type":"extension"}},{"name":"cartesianSelect9","qualifiedName":"darq.SetIterableExtensions.cartesianSelect9","href":"darq/SetIterableExtensions/cartesianSelect9.html","type":"method","overriddenDepth":0,"enclosedBy":{"name":"SetIterableExtensions","type":"extension"}},{"name":"distinct","qualifiedName":"darq.SetIterableExtensions.distinct","href":"darq/SetIterableExtensions/distinct.html","type":"method","overriddenDepth":0,"enclosedBy":{"name":"SetIterableExtensions","type":"extension"}},{"name":"except","qualifiedName":"darq.SetIterableExtensions.except","href":"darq/SetIterableExtensions/except.html","type":"method","overriddenDepth":0,"enclosedBy":{"name":"SetIterableExtensions","type":"extension"}},{"name":"intersect","qualifiedName":"darq.SetIterableExtensions.intersect","href":"darq/SetIterableExtensions/intersect.html","type":"method","overriddenDepth":0,"enclosedBy":{"name":"SetIterableExtensions","type":"extension"}},{"name":"permutations","qualifiedName":"darq.SetIterableExtensions.permutations","href":"darq/SetIterableExtensions/permutations.html","type":"method","overriddenDepth":0,"enclosedBy":{"name":"SetIterableExtensions","type":"extension"}},{"name":"subsets","qualifiedName":"darq.SetIterableExtensions.subsets","href":"darq/SetIterableExtensions/subsets.html","type":"method","overriddenDepth":0,"enclosedBy":{"name":"SetIterableExtensions","type":"extension"}},{"name":"union","qualifiedName":"darq.SetIterableExtensions.union","href":"darq/SetIterableExtensions/union.html","type":"method","overriddenDepth":0,"enclosedBy":{"name":"SetIterableExtensions","type":"extension"}},{"name":"Sorter","qualifiedName":"darq.Sorter","href":"darq/Sorter.html","type":"typedef","overriddenDepth":0,"enclosedBy":{"name":"darq","type":"library"}},{"name":"StringExtensions","qualifiedName":"darq.StringExtensions","href":"darq/StringExtensions.html","type":"extension","overriddenDepth":0,"enclosedBy":{"name":"darq","type":"library"}},{"name":"iterable","qualifiedName":"darq.StringExtensions.iterable","href":"darq/StringExtensions/iterable.html","type":"property","overriddenDepth":0,"enclosedBy":{"name":"StringExtensions","type":"extension"}},{"name":"iterableRunes","qualifiedName":"darq.StringExtensions.iterableRunes","href":"darq/StringExtensions/iterableRunes.html","type":"property","overriddenDepth":0,"enclosedBy":{"name":"StringExtensions","type":"extension"}}]
